itkwasm_transform_emscripten/__init__.py
itkwasm_transform_emscripten/_version.py
itkwasm_transform_emscripten/affine_ops_async.py
itkwasm_transform_emscripten/create_affine_transform_async.py
itkwasm_transform_emscripten/create_azimuth_elevation_to_cartesian_transform_async.py
itkwasm_transform_emscripten/create_bspline_smoothing_on_update_displacement_field_transform_async.py
itkwasm_transform_emscripten/create_bspline_transform_async.py
itkwasm_transform_emscripten/create_composite_transform_async.py
itkwasm_transform_emscripten/create_constant_velocity_field_transform_async.py
itkwasm_transform_emscripten/create_displacement_field_transform_async.py
itkwasm_transform_emscripten/create_euler2d_transform_async.py
itkwasm_transform_emscripten/create_euler3d_transform_async.py
itkwasm_transform_emscripten/create_gaussian_exponential_diffeomorphic_transform_async.py
itkwasm_transform_emscripten/create_gaussian_smoothing_on_update_displacement_field_transform_async.py
itkwasm_transform_emscripten/create_gaussian_smoothing_on_update_time_varying_velocity_field_transform_async.py
itkwasm_transform_emscripten/create_identity_transform_async.py
itkwasm_transform_emscripten/create_quaternion_rigid_transform_async.py
itkwasm_transform_emscripten/create_rigid2d_transform_async.py
itkwasm_transform_emscripten/create_rigid3d_perspective_transform_async.py
itkwasm_transform_emscripten/create_rigid3d_transform_async.py
itkwasm_transform_emscripten/create_scalable_affine_transform_async.py
itkwasm_transform_emscripten/create_scale_logarithmic_transform_async.py
itkwasm_transform_emscripten/create_scale_skew_versor3d_transform_async.py
itkwasm_transform_emscripten/create_scale_transform_async.py
itkwasm_transform_emscripten/create_similarity2d_transform_async.py
itkwasm_transform_emscripten/create_similarity3d_transform_async.py
itkwasm_transform_emscripten/create_time_varying_velocity_field_transform_async.py
itkwasm_transform_emscripten/create_translation_transform_async.py
itkwasm_transform_emscripten-0.1.0.dist-info/METADATA
itkwasm_transform_emscripten-0.1.0.dist-info/WHEEL
itkwasm_transform_emscripten-0.1.0.dist-info/RECORD
